{
  "atualizado_em": "2026-05-14T17:38:56.614Z",
  "total": 27,
  "membros": [
    {
      "nome": "Laércio",
      "aniversario": {
        "dia": 8,
        "mes": 2
      }
    },
    {
      "nome": "Alexandre Melillo Lopes",
      "aniversario": null
    },
    {
      "nome": "Jardim",
      "aniversario": null
    },
    {
      "nome": "Jovail Vilela",
      "aniversario": null
    },
    {
      "nome": "Leonardo Farias",
      "aniversario": null
    },
    {
      "nome": "Luiz Henrique de Barros",
      "aniversario": null
    },
    {
      "nome": "Max",
      "aniversario": null
    },
    {
      "nome": "Roberto Amorim",
      "aniversario": null
    },
    {
      "nome": "Uélito Borboleta",
      "aniversario": null
    },
    {
      "nome": "Wlamir Silva",
      "aniversario": null
    },
    {
      "nome": "Armínio TUPAL",
      "aniversario": null
    },
    {
      "nome": "Augusto TUPAL",
      "aniversario": null
    },
    {
      "nome": "Dario Araujo",
      "aniversario": null
    },
    {
      "nome": "Érica",
      "aniversario": null
    },
    {
      "nome": "Marco Lopes",
      "aniversario": null
    },
    {
      "nome": "Marco Torres",
      "aniversario": null
    },
    {
      "nome": "Marcos Eduardo de Carvalho",
      "aniversario": null
    },
    {
      "nome": "Roberto Monteiro",
      "aniversario": null
    },
    {
      "nome": "Rodrigo TUPAL",
      "aniversario": null
    },
    {
      "nome": "Rubens Mazer",
      "aniversario": null
    },
    {
      "nome": "Wellington Papa",
      "aniversario": null
    },
    {
      "nome": "Zaqueu SUMPE",
      "aniversario": null
    },
    {
      "nome": "Carlinhos",
      "aniversario": null
    },
    {
      "nome": "José Renato - ZeGrande",
      "aniversario": null
    },
    {
      "nome": "Marcio Vantil",
      "aniversario": null
    },
    {
      "nome": "Marcus Gaze",
      "aniversario": null
    },
    {
      "nome": "Sérgio Nogueira",
      "aniversario": null
    }
  ]
}
